tester_mdio.v
module tester_mdio (
    output reg clk, reset, mdio_start, mdio_in,
    output reg [31:0] t_data,
    input mdc, mdio_out, mdio_oe,
    input [15:0] rd_data,
    input data_rdy
);

//acá se definen las pruebas que se van a realizar
always begin//inicializamos el clk
    #20 clk = ~clk;
end

initial begin
    clk = 0;
    reset = 0;

    #20 reset = 1;
    #40 reset = 0;
        mdio_start = 0;

        //para escritura
        t_data = 32'h55555555;
    #80 mdio_start = 1;
    #40 mdio_start= 0;
    #7800 t_data = 32'h65557777;
        
    #160 mdio_start = 1;
    #40 mdio_start = 0;

    //para lectura
    #15 mdio_in =1; //15  Acá se inicia la transacción de lectura
    #10 mdio_in =0;  //14
    #10 mdio_in =1;  //13
    #10 mdio_in =0;  //12
    #10 mdio_in =1;  //11
    #10 mdio_in =0;  //10
    #10 mdio_in =1;  //9
    #10 mdio_in =0;  //8
    #10 mdio_in =1;  //7
    #10 mdio_in =0;  //6
    #10 mdio_in =1;  //5
    #10 mdio_in =0;  //4
    #10 mdio_in =0;  //3
    #10 mdio_in =1;  //2
    #10 mdio_in =1;  //1
    #10 mdio_in =0;  //0
    //mdio_in = 32'h55555555;
    #8000; 
    $finish;
end
endmodule

generador_mdio.v
module generador_mdio (
    input clk,reset, mdio_start, mdio_in,
    input [31:0] t_data,
    output mdc, mdio_out, mdio_oe,
    output reg [15:0] rd_data,
    output reg data_rdy
);

//definimos los estados de la máquina con la que manejaremos el módulo
localparam INICIO = 3'b001;
localparam LECTURA = 3'b010;
localparam ESCRITURA = 3'b100;

//definimos variables internas
reg [1:0] clk_count;
reg [4:0] bit_count, next_bit_count;
reg [2:0] state, next_state;
reg mdio_out, mdio_oe;
wire write; //cuando estamos en modo escritura: write = 1
reg mdc_anterior;
wire posedge_mdc; //los datos los transmitimos en el posedge del mdc
wire trans_finalizada;
reg [15:0] next_dato_rec;

always @ (posedge clk) begin //funcionamiento del reset
    if (reset) begin
        clk_count <= 2'b00;
        state <= INICIO;
        mdc_anterior <= 0;
        bit_count <= 5'h00;
        rd_data <= 16'h0000;
    end
    else begin
        clk_count <= clk_count + 1;
        state <= next_state;
        mdc_anterior <= mdc;
        bit_count <= next_bit_count;
        rd_data <= next_dato_rec;
    end
end

always @ (*) begin
    next_state = state;
    next_bit_count = bit_count;
    mdio_out = t_data[bit_count];
    next_dato_rec = rd_data;
    mdio_oe = 0;

    case (state)
    INICIO: begin
        if (mdio_start & posedge_mdc) begin
            next_bit_count = bit_count + 1;
            mdio_oe = 1;
        end
        if (mdio_start & write & posedge_mdc)
            next_state = ESCRITURA;
        else if (mdio_start & !write & posedge_mdc)
            next_state = LECTURA;
    end

    ESCRITURA: begin
        mdio_oe = 1;
        if(trans_finalizada)
            next_state = INICIO;
        if (posedge_mdc)
            next_bit_count = bit_count + 1;
    end

    LECTURA: begin
        mdio_oe = (bit_count < 16);
        if(trans_finalizada)
            next_state = INICIO;
            data_rdy = 1;
        if (posedge_mdc)
            next_bit_count = bit_count + 1;

        if(mdio_oe)
            /*next_dato_rec[31 - bit_count]*/ rd_data = 32'b0110010101010101;
    end
    endcase
end

assign mdc = clk_count[1]; //mdc a 25% del clk
assign write = ~t_data[29] & t_data[28]; //write = 01
assign posedge_mdc = mdc & ~mdc_anterior;
assign trans_finalizada = (bit_count == 5'h1F);
endmodule

tb_mdio.v
`include "generador_mdio.v"
`include "tester_mdio.v"

module mdio_tb;

wire clk, reset, mdio_start;
wire [31:0] t_data;
wire        mdc, mdio_out, mdio_oe, mdio_in, data_rdy;
wire [15:0] rd_data;

generador_mdio DUT (
    .clk(clk),
    .reset(reset),
    .mdio_start(mdio_start),
    .t_data(t_data[31:0]),
    .mdc(mdc),
    .mdio_out(mdio_out),
    .mdio_oe(mdio_oe),
    .mdio_in(mdio_in),
    .rd_data(rd_data[15:0]),
    .data_rdy(data_rdy)
);

tester_mdio test (
    .clk(clk),
    .reset(reset),
    .mdio_start(mdio_start),
    .t_data(t_data[31:0]),
    .mdc(mdc),
    .mdio_out(mdio_out),
    .mdio_oe(mdio_oe),
    .mdio_in(mdio_in),
    .rd_data(rd_data[15:0]),
    .data_rdy(data_rdy)
);

initial begin
    $dumpfile("mdio.vcd");
    $dumpvars;
end
endmodule

mdio.vcd
$date
	Mon Jul  1 19:55:45 2024
$end
$version
	Icarus Verilog
$end
$timescale
	1s
$end
$scope module mdio_tb $end
$var wire 32 ! t_data [31:0] $end
$var wire 1 " reset $end
$var wire 16 # rd_data [15:0] $end
$var wire 1 $ mdio_start $end
$var wire 1 % mdio_out $end
$var wire 1 & mdio_oe $end
$var wire 1 ' mdio_in $end
$var wire 1 ( mdc $end
$var wire 1 ) data_rdy $end
$var wire 1 * clk $end
$scope module DUT $end
$var wire 1 + posedge_mdc $end
$var wire 1 , write $end
$var wire 1 - trans_finalizada $end
$var wire 32 . t_data [31:0] $end
$var wire 1 " reset $end
$var wire 1 $ mdio_start $end
$var wire 1 ' mdio_in $end
$var wire 1 ( mdc $end
$var wire 1 * clk $end
$var reg 5 / bit_count [4:0] $end
$var reg 2 0 clk_count [1:0] $end
$var reg 1 ) data_rdy $end
$var reg 1 1 mdc_anterior $end
$var reg 1 & mdio_oe $end
$var reg 1 % mdio_out $end
$var reg 5 2 next_bit_count [4:0] $end
$var reg 16 3 next_dato_rec [15:0] $end
$var reg 3 4 next_state [2:0] $end
$var reg 16 5 rd_data [15:0] $end
$var reg 3 6 state [2:0] $end
$upscope $end
$scope module test $end
$var wire 1 ) data_rdy $end
$var wire 1 ( mdc $end
$var wire 1 & mdio_oe $end
$var wire 1 % mdio_out $end
$var wire 16 7 rd_data [15:0] $end
$var reg 1 * clk $end
$var reg 1 ' mdio_in $end
$var reg 1 $ mdio_start $end
$var reg 1 " reset $end
$var reg 32 8 t_data [31:0] $end
$upscope $end
$upscope $end
$enddefinitions $end
#0
$dumpvars
bx 8
bx 7
bx 6
bx 5
bx 4
bx 3
bx 2
x1
bx 0
bx /
bx .
x-
x,
x+
0*
x)
x(
x'
x&
x%
x$
bx #
0"
bx !
$end
#20
0+
0&
b0 3
b0 2
b1 4
0(
b0 #
b0 5
b0 7
0-
b0 /
01
b1 6
b0 0
1"
1*
#40
0*
#60
b1 0
1,
1%
1*
b1010101010101010101010101010101 !
b1010101010101010101010101010101 .
b1010101010101010101010101010101 8
0$
0"
#80
0*
#100
1+
1(
b10 0
1*
#120
0*
#140
0+
0%
b1 /
11
b100 6
b11 0
b100 4
1&
b1 2
1*
1$
#160
0*
#180
0(
b0 0
1&
1*
0$
#200
0*
#220
01
b1 0
1*
#240
0*
#260
b10 2
1&
1+
1(
b10 0
1*
#280
0*
#300
0+
b10 2
1&
1%
b10 /
11
b11 0
1*
#320
0*
#340
0(
b0 0
1*
#360
0*
#380
01
b1 0
1*
#400
0*
#420
b11 2
1&
1+
1(
b10 0
1*
#440
0*
#460
0+
b11 2
1&
0%
b11 /
11
b11 0
1*
#480
0*
#500
0(
b0 0
1*
#520
0*
#540
01
b1 0
1*
#560
0*
#580
b100 2
1&
1+
1(
b10 0
1*
#600
0*
#620
0+
b100 2
1&
1%
b100 /
11
b11 0
1*
#640
0*
#660
0(
b0 0
1*
#680
0*
#700
01
b1 0
1*
#720
0*
#740
b101 2
1&
1+
1(
b10 0
1*
#760
0*
#780
0+
b101 2
1&
0%
b101 /
11
b11 0
1*
#800
0*
#820
0(
b0 0
1*
#840
0*
#860
01
b1 0
1*
#880
0*
#900
b110 2
1&
1+
1(
b10 0
1*
#920
0*
#940
0+
b110 2
1&
1%
b110 /
11
b11 0
1*
#960
0*
#980
0(
b0 0
1*
#1000
0*
#1020
01
b1 0
1*
#1040
0*
#1060
b111 2
1&
1+
1(
b10 0
1*
#1080
0*
#1100
0+
b111 2
1&
0%
b111 /
11
b11 0
1*
#1120
0*
#1140
0(
b0 0
1*
#1160
0*
#1180
01
b1 0
1*
#1200
0*
#1220
b1000 2
1&
1+
1(
b10 0
1*
#1240
0*
#1260
0+
b1000 2
1&
1%
b1000 /
11
b11 0
1*
#1280
0*
#1300
0(
b0 0
1*
#1320
0*
#1340
01
b1 0
1*
#1360
0*
#1380
b1001 2
1&
1+
1(
b10 0
1*
#1400
0*
#1420
0+
b1001 2
1&
0%
b1001 /
11
b11 0
1*
#1440
0*
#1460
0(
b0 0
1*
#1480
0*
#1500
01
b1 0
1*
#1520
0*
#1540
b1010 2
1&
1+
1(
b10 0
1*
#1560
0*
#1580
0+
b1010 2
1&
1%
b1010 /
11
b11 0
1*
#1600
0*
#1620
0(
b0 0
1*
#1640
0*
#1660
01
b1 0
1*
#1680
0*
#1700
b1011 2
1&
1+
1(
b10 0
1*
#1720
0*
#1740
0+
b1011 2
1&
0%
b1011 /
11
b11 0
1*
#1760
0*
#1780
0(
b0 0
1*
#1800
0*
#1820
01
b1 0
1*
#1840
0*
#1860
b1100 2
1&
1+
1(
b10 0
1*
#1880
0*
#1900
0+
b1100 2
1&
1%
b1100 /
11
b11 0
1*
#1920
0*
#1940
0(
b0 0
1*
#1960
0*
#1980
01
b1 0
1*
#2000
0*
#2020
b1101 2
1&
1+
1(
b10 0
1*
#2040
0*
#2060
0+
b1101 2
1&
0%
b1101 /
11
b11 0
1*
#2080
0*
#2100
0(
b0 0
1*
#2120
0*
#2140
01
b1 0
1*
#2160
0*
#2180
b1110 2
1&
1+
1(
b10 0
1*
#2200
0*
#2220
0+
b1110 2
1&
1%
b1110 /
11
b11 0
1*
#2240
0*
#2260
0(
b0 0
1*
#2280
0*
#2300
01
b1 0
1*
#2320
0*
#2340
b1111 2
1&
1+
1(
b10 0
1*
#2360
0*
#2380
0+
b1111 2
1&
0%
b1111 /
11
b11 0
1*
#2400
0*
#2420
0(
b0 0
1*
#2440
0*
#2460
01
b1 0
1*
#2480
0*
#2500
b10000 2
1&
1+
1(
b10 0
1*
#2520
0*
#2540
0+
b10000 2
1&
1%
b10000 /
11
b11 0
1*
#2560
0*
#2580
0(
b0 0
1*
#2600
0*
#2620
01
b1 0
1*
#2640
0*
#2660
b10001 2
1&
1+
1(
b10 0
1*
#2680
0*
#2700
0+
b10001 2
1&
0%
b10001 /
11
b11 0
1*
#2720
0*
#2740
0(
b0 0
1*
#2760
0*
#2780
01
b1 0
1*
#2800
0*
#2820
b10010 2
1&
1+
1(
b10 0
1*
#2840
0*
#2860
0+
b10010 2
1&
1%
b10010 /
11
b11 0
1*
#2880
0*
#2900
0(
b0 0
1*
#2920
0*
#2940
01
b1 0
1*
#2960
0*
#2980
b10011 2
1&
1+
1(
b10 0
1*
#3000
0*
#3020
0+
b10011 2
1&
0%
b10011 /
11
b11 0
1*
#3040
0*
#3060
0(
b0 0
1*
#3080
0*
#3100
01
b1 0
1*
#3120
0*
#3140
b10100 2
1&
1+
1(
b10 0
1*
#3160
0*
#3180
0+
b10100 2
1&
1%
b10100 /
11
b11 0
1*
#3200
0*
#3220
0(
b0 0
1*
#3240
0*
#3260
01
b1 0
1*
#3280
0*
#3300
b10101 2
1&
1+
1(
b10 0
1*
#3320
0*
#3340
0+
b10101 2
1&
0%
b10101 /
11
b11 0
1*
#3360
0*
#3380
0(
b0 0
1*
#3400
0*
#3420
01
b1 0
1*
#3440
0*
#3460
b10110 2
1&
1+
1(
b10 0
1*
#3480
0*
#3500
0+
b10110 2
1&
1%
b10110 /
11
b11 0
1*
#3520
0*
#3540
0(
b0 0
1*
#3560
0*
#3580
01
b1 0
1*
#3600
0*
#3620
b10111 2
1&
1+
1(
b10 0
1*
#3640
0*
#3660
0+
b10111 2
1&
0%
b10111 /
11
b11 0
1*
#3680
0*
#3700
0(
b0 0
1*
#3720
0*
#3740
01
b1 0
1*
#3760
0*
#3780
b11000 2
1&
1+
1(
b10 0
1*
#3800
0*
#3820
0+
b11000 2
1&
1%
b11000 /
11
b11 0
1*
#3840
0*
#3860
0(
b0 0
1*
#3880
0*
#3900
01
b1 0
1*
#3920
0*
#3940
b11001 2
1&
1+
1(
b10 0
1*
#3960
0*
#3980
0+
b11001 2
1&
0%
b11001 /
11
b11 0
1*
#4000
0*
#4020
0(
b0 0
1*
#4040
0*
#4060
01
b1 0
1*
#4080
0*
#4100
b11010 2
1&
1+
1(
b10 0
1*
#4120
0*
#4140
0+
b11010 2
1&
1%
b11010 /
11
b11 0
1*
#4160
0*
#4180
0(
b0 0
1*
#4200
0*
#4220
01
b1 0
1*
#4240
0*
#4260
b11011 2
1&
1+
1(
b10 0
1*
#4280
0*
#4300
0+
b11011 2
1&
0%
b11011 /
11
b11 0
1*
#4320
0*
#4340
0(
b0 0
1*
#4360
0*
#4380
01
b1 0
1*
#4400
0*
#4420
b11100 2
1&
1+
1(
b10 0
1*
#4440
0*
#4460
0+
b11100 2
1&
1%
b11100 /
11
b11 0
1*
#4480
0*
#4500
0(
b0 0
1*
#4520
0*
#4540
01
b1 0
1*
#4560
0*
#4580
b11101 2
1&
1+
1(
b10 0
1*
#4600
0*
#4620
0+
b11101 2
1&
0%
b11101 /
11
b11 0
1*
#4640
0*
#4660
0(
b0 0
1*
#4680
0*
#4700
01
b1 0
1*
#4720
0*
#4740
b11110 2
1&
1+
1(
b10 0
1*
#4760
0*
#4780
0+
b11110 2
1&
1%
b11110 /
11
b11 0
1*
#4800
0*
#4820
0(
b0 0
1*
#4840
0*
#4860
01
b1 0
1*
#4880
0*
#4900
b11111 2
1&
1+
1(
b10 0
1*
#4920
0*
#4940
0+
b11111 2
b1 4
1&
0%
1-
b11111 /
11
b11 0
1*
#4960
0*
#4980
0&
0(
b1 6
b0 0
1*
#5000
0*
#5020
01
b1 0
1*
#5040
0*
#5060
1+
1(
b10 0
1*
#5080
0*
#5100
0+
11
b11 0
1*
#5120
0*
#5140
0(
b0 0
1*
#5160
0*
#5180
01
b1 0
1*
#5200
0*
#5220
1+
1(
b10 0
1*
#5240
0*
#5260
0+
11
b11 0
1*
#5280
0*
#5300
0(
b0 0
1*
#5320
0*
#5340
01
b1 0
1*
#5360
0*
#5380
1+
1(
b10 0
1*
#5400
0*
#5420
0+
11
b11 0
1*
#5440
0*
#5460
0(
b0 0
1*
#5480
0*
#5500
01
b1 0
1*
#5520
0*
#5540
1+
1(
b10 0
1*
#5560
0*
#5580
0+
11
b11 0
1*
#5600
0*
#5620
0(
b0 0
1*
#5640
0*
#5660
01
b1 0
1*
#5680
0*
#5700
1+
1(
b10 0
1*
#5720
0*
#5740
0+
11
b11 0
1*
#5760
0*
#5780
0(
b0 0
1*
#5800
0*
#5820
01
b1 0
1*
#5840
0*
#5860
1+
1(
b10 0
1*
#5880
0*
#5900
0+
11
b11 0
1*
#5920
0*
#5940
0(
b0 0
1*
#5960
0*
#5980
01
b1 0
1*
#6000
0*
#6020
1+
1(
b10 0
1*
#6040
0*
#6060
0+
11
b11 0
1*
#6080
0*
#6100
0(
b0 0
1*
#6120
0*
#6140
01
b1 0
1*
#6160
0*
#6180
1+
1(
b10 0
1*
#6200
0*
#6220
0+
11
b11 0
1*
#6240
0*
#6260
0(
b0 0
1*
#6280
0*
#6300
01
b1 0
1*
#6320
0*
#6340
1+
1(
b10 0
1*
#6360
0*
#6380
0+
11
b11 0
1*
#6400
0*
#6420
0(
b0 0
1*
#6440
0*
#6460
01
b1 0
1*
#6480
0*
#6500
1+
1(
b10 0
1*
#6520
0*
#6540
0+
11
b11 0
1*
#6560
0*
#6580
0(
b0 0
1*
#6600
0*
#6620
01
b1 0
1*
#6640
0*
#6660
1+
1(
b10 0
1*
#6680
0*
#6700
0+
11
b11 0
1*
#6720
0*
#6740
0(
b0 0
1*
#6760
0*
#6780
01
b1 0
1*
#6800
0*
#6820
1+
1(
b10 0
1*
#6840
0*
#6860
0+
11
b11 0
1*
#6880
0*
#6900
0(
b0 0
1*
#6920
0*
#6940
01
b1 0
1*
#6960
0*
#6980
1+
1(
b10 0
1*
#7000
0*
#7020
0+
11
b11 0
1*
#7040
0*
#7060
0(
b0 0
1*
#7080
0*
#7100
01
b1 0
1*
#7120
0*
#7140
1+
1(
b10 0
1*
#7160
0*
#7180
0+
11
b11 0
1*
#7200
0*
#7220
0(
b0 0
1*
#7240
0*
#7260
01
b1 0
1*
#7280
0*
#7300
1+
1(
b10 0
1*
#7320
0*
#7340
0+
11
b11 0
1*
#7360
0*
#7380
0(
b0 0
1*
#7400
0*
#7420
01
b1 0
1*
#7440
0*
#7460
1+
1(
b10 0
1*
#7480
0*
#7500
0+
11
b11 0
1*
#7520
0*
#7540
0(
b0 0
1*
#7560
0*
#7580
01
b1 0
1*
#7600
0*
#7620
1+
1(
b10 0
1*
#7640
0*
#7660
0+
11
b11 0
1*
#7680
0*
#7700
0(
b0 0
1*
#7720
0*
#7740
01
b1 0
1*
#7760
0*
#7780
1+
1(
b10 0
1*
#7800
0*
#7820
0+
11
b11 0
1*
#7840
0*
#7860
0(
b0 0
1*
#7880
0*
#7900
01
b1 0
1*
#7920
0*
#7940
1+
1(
b10 0
1*
#7960
0*
#7980
0+
11
b11 0
0,
1*
b1100101010101010111011101110111 !
b1100101010101010111011101110111 .
b1100101010101010111011101110111 8
#8000
0*
#8020
0(
b0 0
1*
#8040
0*
#8060
01
b1 0
1*
#8080
0*
#8100
1+
1(
b10 0
1*
#8120
0*
#8140
b110010101010101 3
0+
b110010101010101 #
b110010101010101 5
b110010101010101 7
1)
1%
0-
b0 /
11
b10 6
b11 0
b10 4
1&
b0 2
1*
1$
#8160
0*
#8180
0(
b0 0
1&
1*
0$
#8195
1'
#8200
0*
#8205
0'
#8215
1'
#8220
01
b1 0
1*
#8225
0'
#8235
1'
#8240
0*
#8245
0'
#8255
1'
#8260
b1 2
1&
1+
1(
b10 0
1*
#8265
0'
#8275
1'
#8280
0*
#8285
0'
#8295
1'
#8300
0+
b1 2
1&
b1 /
11
b11 0
1*
#8305
0'
#8320
0*
#8325
1'
#8340
0(
b0 0
1*
#8345
0'
#8360
0*
#8380
01
b1 0
1*
#8400
0*
#8420
b10 2
1&
1+
1(
b10 0
1*
#8440
0*
#8460
0+
b10 2
1&
b10 /
11
b11 0
1*
#8480
0*
#8500
0(
b0 0
1*
#8520
0*
#8540
01
b1 0
1*
#8560
0*
#8580
b11 2
1&
1+
1(
b10 0
1*
#8600
0*
#8620
0+
b11 2
1&
0%
b11 /
11
b11 0
1*
#8640
0*
#8660
0(
b0 0
1*
#8680
0*
#8700
01
b1 0
1*
#8720
0*
#8740
b100 2
1&
1+
1(
b10 0
1*
#8760
0*
#8780
0+
b100 2
1&
1%
b100 /
11
b11 0
1*
#8800
0*
#8820
0(
b0 0
1*
#8840
0*
#8860
01
b1 0
1*
#8880
0*
#8900
b101 2
1&
1+
1(
b10 0
1*
#8920
0*
#8940
0+
b101 2
1&
b101 /
11
b11 0
1*
#8960
0*
#8980
0(
b0 0
1*
#9000
0*
#9020
01
b1 0
1*
#9040
0*
#9060
b110 2
1&
1+
1(
b10 0
1*
#9080
0*
#9100
0+
b110 2
1&
b110 /
11
b11 0
1*
#9120
0*
#9140
0(
b0 0
1*
#9160
0*
#9180
01
b1 0
1*
#9200
0*
#9220
b111 2
1&
1+
1(
b10 0
1*
#9240
0*
#9260
0+
b111 2
1&
0%
b111 /
11
b11 0
1*
#9280
0*
#9300
0(
b0 0
1*
#9320
0*
#9340
01
b1 0
1*
#9360
0*
#9380
b1000 2
1&
1+
1(
b10 0
1*
#9400
0*
#9420
0+
b1000 2
1&
1%
b1000 /
11
b11 0
1*
#9440
0*
#9460
0(
b0 0
1*
#9480
0*
#9500
01
b1 0
1*
#9520
0*
#9540
b1001 2
1&
1+
1(
b10 0
1*
#9560
0*
#9580
0+
b1001 2
1&
b1001 /
11
b11 0
1*
#9600
0*
#9620
0(
b0 0
1*
#9640
0*
#9660
01
b1 0
1*
#9680
0*
#9700
b1010 2
1&
1+
1(
b10 0
1*
#9720
0*
#9740
0+
b1010 2
1&
b1010 /
11
b11 0
1*
#9760
0*
#9780
0(
b0 0
1*
#9800
0*
#9820
01
b1 0
1*
#9840
0*
#9860
b1011 2
1&
1+
1(
b10 0
1*
#9880
0*
#9900
0+
b1011 2
1&
0%
b1011 /
11
b11 0
1*
#9920
0*
#9940
0(
b0 0
1*
#9960
0*
#9980
01
b1 0
1*
#10000
0*
#10020
b1100 2
1&
1+
1(
b10 0
1*
#10040
0*
#10060
0+
b1100 2
1&
1%
b1100 /
11
b11 0
1*
#10080
0*
#10100
0(
b0 0
1*
#10120
0*
#10140
01
b1 0
1*
#10160
0*
#10180
b1101 2
1&
1+
1(
b10 0
1*
#10200
0*
#10220
0+
b1101 2
1&
b1101 /
11
b11 0
1*
#10240
0*
#10260
0(
b0 0
1*
#10280
0*
#10300
01
b1 0
1*
#10320
0*
#10340
b1110 2
1&
1+
1(
b10 0
1*
#10360
0*
#10380
0+
b1110 2
1&
b1110 /
11
b11 0
1*
#10400
0*
#10420
0(
b0 0
1*
#10440
0*
#10460
01
b1 0
1*
#10480
0*
#10500
b1111 2
1&
1+
1(
b10 0
1*
#10520
0*
#10540
0+
b1111 2
1&
0%
b1111 /
11
b11 0
1*
#10560
0*
#10580
0(
b0 0
1*
#10600
0*
#10620
01
b1 0
1*
#10640
0*
#10660
b10000 2
1&
1+
1(
b10 0
1*
#10680
0*
#10700
0+
b10000 2
0&
1%
b10000 /
11
b11 0
1*
#10720
0*
#10740
0(
b0 0
1*
#10760
0*
#10780
01
b1 0
1*
#10800
0*
#10820
b10001 2
1+
1(
b10 0
1*
#10840
0*
#10860
0+
b10001 2
0%
b10001 /
11
b11 0
1*
#10880
0*
#10900
0(
b0 0
1*
#10920
0*
#10940
01
b1 0
1*
#10960
0*
#10980
b10010 2
1+
1(
b10 0
1*
#11000
0*
#11020
0+
b10010 2
1%
b10010 /
11
b11 0
1*
#11040
0*
#11060
0(
b0 0
1*
#11080
0*
#11100
01
b1 0
1*
#11120
0*
#11140
b10011 2
1+
1(
b10 0
1*
#11160
0*
#11180
0+
b10011 2
0%
b10011 /
11
b11 0
1*
#11200
0*
#11220
0(
b0 0
1*
#11240
0*
#11260
01
b1 0
1*
#11280
0*
#11300
b10100 2
1+
1(
b10 0
1*
#11320
0*
#11340
0+
b10100 2
1%
b10100 /
11
b11 0
1*
#11360
0*
#11380
0(
b0 0
1*
#11400
0*
#11420
01
b1 0
1*
#11440
0*
#11460
b10101 2
1+
1(
b10 0
1*
#11480
0*
#11500
0+
b10101 2
0%
b10101 /
11
b11 0
1*
#11520
0*
#11540
0(
b0 0
1*
#11560
0*
#11580
01
b1 0
1*
#11600
0*
#11620
b10110 2
1+
1(
b10 0
1*
#11640
0*
#11660
0+
b10110 2
1%
b10110 /
11
b11 0
1*
#11680
0*
#11700
0(
b0 0
1*
#11720
0*
#11740
01
b1 0
1*
#11760
0*
#11780
b10111 2
1+
1(
b10 0
1*
#11800
0*
#11820
0+
b10111 2
0%
b10111 /
11
b11 0
1*
#11840
0*
#11860
0(
b0 0
1*
#11880
0*
#11900
01
b1 0
1*
#11920
0*
#11940
b11000 2
1+
1(
b10 0
1*
#11960
0*
#11980
0+
b11000 2
1%
b11000 /
11
b11 0
1*
#12000
0*
#12020
0(
b0 0
1*
#12040
0*
#12060
01
b1 0
1*
#12080
0*
#12100
b11001 2
1+
1(
b10 0
1*
#12120
0*
#12140
0+
b11001 2
0%
b11001 /
11
b11 0
1*
#12160
0*
#12180
0(
b0 0
1*
#12200
0*
#12220
01
b1 0
1*
#12240
0*
#12260
b11010 2
1+
1(
b10 0
1*
#12280
0*
#12300
0+
b11010 2
1%
b11010 /
11
b11 0
1*
#12320
0*
#12340
0(
b0 0
1*
#12360
0*
#12380
01
b1 0
1*
#12400
0*
#12420
b11011 2
1+
1(
b10 0
1*
#12440
0*
#12460
0+
b11011 2
0%
b11011 /
11
b11 0
1*
#12480
0*
#12500
0(
b0 0
1*
#12520
0*
#12540
01
b1 0
1*
#12560
0*
#12580
b11100 2
1+
1(
b10 0
1*
#12600
0*
#12620
0+
b11100 2
b11100 /
11
b11 0
1*
#12640
0*
#12660
0(
b0 0
1*
#12680
0*
#12700
01
b1 0
1*
#12720
0*
#12740
b11101 2
1+
1(
b10 0
1*
#12760
0*
#12780
0+
b11101 2
1%
b11101 /
11
b11 0
1*
#12800
0*
#12820
0(
b0 0
1*
#12840
0*
#12860
01
b1 0
1*
#12880
0*
#12900
b11110 2
1+
1(
b10 0
1*
#12920
0*
#12940
0+
b11110 2
b11110 /
11
b11 0
1*
#12960
0*
#12980
0(
b0 0
1*
#13000
0*
#13020
01
b1 0
1*
#13040
0*
#13060
b11111 2
1+
1(
b10 0
1*
#13080
0*
#13100
0+
b11111 2
b1 4
0%
1-
b11111 /
11
b11 0
1*
#13120
0*
#13140
0(
b1 6
b0 0
1*
#13160
0*
#13180
01
b1 0
1*
#13200
0*
#13220
1+
1(
b10 0
1*
#13240
0*
#13260
0+
11
b11 0
1*
#13280
0*
#13300
0(
b0 0
1*
#13320
0*
#13340
01
b1 0
1*
#13360
0*
#13380
1+
1(
b10 0
1*
#13400
0*
#13420
0+
11
b11 0
1*
#13440
0*
#13460
0(
b0 0
1*
#13480
0*
#13500
01
b1 0
1*
#13520
0*
#13540
1+
1(
b10 0
1*
#13560
0*
#13580
0+
11
b11 0
1*
#13600
0*
#13620
0(
b0 0
1*
#13640
0*
#13660
01
b1 0
1*
#13680
0*
#13700
1+
1(
b10 0
1*
#13720
0*
#13740
0+
11
b11 0
1*
#13760
0*
#13780
0(
b0 0
1*
#13800
0*
#13820
01
b1 0
1*
#13840
0*
#13860
1+
1(
b10 0
1*
#13880
0*
#13900
0+
11
b11 0
1*
#13920
0*
#13940
0(
b0 0
1*
#13960
0*
#13980
01
b1 0
1*
#14000
0*
#14020
1+
1(
b10 0
1*
#14040
0*
#14060
0+
11
b11 0
1*
#14080
0*
#14100
0(
b0 0
1*
#14120
0*
#14140
01
b1 0
1*
#14160
0*
#14180
1+
1(
b10 0
1*
#14200
0*
#14220
0+
11
b11 0
1*
#14240
0*
#14260
0(
b0 0
1*
#14280
0*
#14300
01
b1 0
1*
#14320
0*
#14340
1+
1(
b10 0
1*
#14360
0*
#14380
0+
11
b11 0
1*
#14400
0*
#14420
0(
b0 0
1*
#14440
0*
#14460
01
b1 0
1*
#14480
0*
#14500
1+
1(
b10 0
1*
#14520
0*
#14540
0+
11
b11 0
1*
#14560
0*
#14580
0(
b0 0
1*
#14600
0*
#14620
01
b1 0
1*
#14640
0*
#14660
1+
1(
b10 0
1*
#14680
0*
#14700
0+
11
b11 0
1*
#14720
0*
#14740
0(
b0 0
1*
#14760
0*
#14780
01
b1 0
1*
#14800
0*
#14820
1+
1(
b10 0
1*
#14840
0*
#14860
0+
11
b11 0
1*
#14880
0*
#14900
0(
b0 0
1*
#14920
0*
#14940
01
b1 0
1*
#14960
0*
#14980
1+
1(
b10 0
1*
#15000
0*
#15020
0+
11
b11 0
1*
#15040
0*
#15060
0(
b0 0
1*
#15080
0*
#15100
01
b1 0
1*
#15120
0*
#15140
1+
1(
b10 0
1*
#15160
0*
#15180
0+
11
b11 0
1*
#15200
0*
#15220
0(
b0 0
1*
#15240
0*
#15260
01
b1 0
1*
#15280
0*
#15300
1+
1(
b10 0
1*
#15320
0*
#15340
0+
11
b11 0
1*
#15360
0*
#15380
0(
b0 0
1*
#15400
0*
#15420
01
b1 0
1*
#15440
0*
#15460
1+
1(
b10 0
1*
#15480
0*
#15500
0+
11
b11 0
1*
#15520
0*
#15540
0(
b0 0
1*
#15560
0*
#15580
01
b1 0
1*
#15600
0*
#15620
1+
1(
b10 0
1*
#15640
0*
#15660
0+
11
b11 0
1*
#15680
0*
#15700
0(
b0 0
1*
#15720
0*
#15740
01
b1 0
1*
#15760
0*
#15780
1+
1(
b10 0
1*
#15800
0*
#15820
0+
11
b11 0
1*
#15840
0*
#15860
0(
b0 0
1*
#15880
0*
#15900
01
b1 0
1*
#15920
0*
#15940
1+
1(
b10 0
1*
#15960
0*
#15980
0+
11
b11 0
1*
#16000
0*
#16020
0(
b0 0
1*
#16040
0*
#16060
01
b1 0
1*
#16080
0*
#16100
1+
1(
b10 0
1*
#16120
0*
#16140
0+
11
b11 0
1*
#16160
0*
#16180
0(
b0 0
1*
#16200
0*
#16220
01
b1 0
1*
#16240
0*
#16260
1+
1(
b10 0
1*
#16280
0*
#16300
0+
11
b11 0
1*
#16320
0*
#16340
0(
b0 0
1*
