DUT.v
module TransMDIO (

input clk,
input reset,
output reg mdc,

output reg MDIO_start,
input [N:0] T_data ,
output reg MDIO_out,
output reg MDIO_oe, 

input MDIO_in,
output reg [(N-1)/2 : 0] RD_data,
output reg data_RDY

);
    //Variables internas para la máquina de estado
    reg [2:0] state;
    reg [2:0] nxt_state;        

    //Variables internas para el proceso de transacción
    reg [N:0] almc ; //Esta variable se encarga de almacenar los valores que se obtienen a la entrada s_in
    reg [5:0] count ;  //Esta variable se encarga de contar los números ingresados a la variable de almacenamiento que posteriormente será cargados en paralelo
    reg freqcounter= 0 ;  //Esta variable se encarga de determinar si la frecuencia de salida se coloca en alto o en bajo
    reg [(N-1)/2 : 0] almLEC ; //Esta variable se encarga de almacenar los valores que serán cargados en RD_data luego del proceso de lectura
    reg [5:0] wrtcount ; //Esta variable se encarga de contar los bits leídos una vez que se comienza con la transferencia MDIO_in

    parameter N = 31 ; //Tamaño de bits de la carga paralela
    parameter freqdiv = 10'd2 ; //Dato por el cual se dividira la frecuencia, en nuestro caso será de 2

    
    //-------------------------------------------------------------------------------------------------------------------------------------------------------------
    //Generacion del mdc, reloj de salida a mitad de frecuencia que la del clk

    always @(posedge clk)
    begin
    freqcounter <= freqcounter + 1; //Se comienza sumando una unidad al contador
    if(freqcounter >= (freqdiv-1)) //Si el contador de frecuencia es igual al divisor -1, el contador de frecuencia pasa a ser 0.
    freqcounter <= 0;
    mdc <= (freqcounter < freqdiv/2)?1'b1:1'b0; //El condicional genera que el mdc se ponga en alto o en bajo cíclicamente gracias a las condiciones anteriores
    end

    //-------------------------------------------------------------------------------------------------------------------------------------------------------------
    //Efecto del RESET

    always @(posedge clk) begin
        
        if (reset == 0) begin //Cuando reset esté en bajo, los valores a continuación se ponen en un estado bajo.
            MDIO_out = 0;
            almc  = T_data; //La variable interna de almacenamiento se vuelve igual a la entrada paralela colocada
            count = 0;
            mdc = 0;
            MDIO_oe = 0;
            RD_data = 0;
            data_RDY = 0;
            almLEC = 0;
            wrtcount = 0;
            
        end    
        else begin //Se quedan como están
            MDIO_out = MDIO_out;
            almc = almc;
            count = count;
            mdc = mdc;
            MDIO_oe = MDIO_oe;
            RD_data = RD_data;
            data_RDY = data_RDY;
            almLEC = almLEC;
            wrtcount = wrtcount;
        end
    end
        

    //-------------------------------------------------------------------------------------------------------------------------------------------------------------
    // Entrada paralela a salida serial

    always @(posedge clk) begin
        
        if (~reset) state <= 3'b001; //Acá se está indicando que cuando el reset sea 0, la señal vuelva al estado de IDLE (que es el estado numero 1). 
        else state <= nxt_state; //Si el reset se encuentra en 1, el FF se mantiene funcionando con normalidad, esperando un flanco para cambiar de estado.
    
    end  

    always @(*) begin 
    
        nxt_state = state;  

        case(state)
            3'b001: begin
                if (T_data[N] == 0) nxt_state = 3'b010;
                else  nxt_state = nxt_state ;   
            end

            3'b010: begin 
                if (T_data[N-1] == 1) nxt_state = 3'b100;   
                else nxt_state = 3'b010; 
            end                                            //Una vez verificado el start, es posible comenzar con la transferencia serial.
            3'b100: begin                      
                        MDIO_start = 1 ;
            end 
            
            default:   nxt_state = 3'b001; // Si la máquina de estados obtuviese un valor de estado distinto o no definido por factores inesperados, este volverá inmediatamente al IDLE. 
        endcase
    end               


    always @(posedge clk) begin
        if((T_data[N:0] == almc[N:0]) && (reset == 1) && (MDIO_start == 1 ))begin  //Dado que queremos que en primera instancia la variable de almacenamiento sea igual a la carga paralela, en el primer flanco se debe cumplir que son iguales 
            MDIO_out = almc[N];                    //Dado que son iguales, se toma la cifra más significativa de la carga en paralelo (que sería la misma de la variable de almacenamiento)
            almc = {almc[N-1:0], 1'b0};               //Acá lo que se hace es mover los bits hacia la izquierda, para que en el siguiente flanco el bit más significativo de la variable de almacenamiento sea realmente
                                                //el segundo bit más significativo de la carga paralela a la entrada
            count = count + 1;                     //Se aumenta en 1 el contador                                   
            end 
            else if ((T_data[N:0] != almc[N:0]) && (reset == 1) && (MDIO_start == 1)) begin   //Por la rotación anterior, en el segundo flanco ya la variable de almacenamiento no será igual a la carga en paralelo, por ende:
                MDIO_out = almc[N];                          //Ahora la salida tomará el valor más significativo en el almacenamiento, que gracias a la rotación es en realidad T_data[N-1] (el segundo más significativo de T_data)
                almc = {almc[N-1:0], 1'b0};                     //Acá se vuelve a rotar. Para el siguiente clock será este else if el que seguirá actuando.
                count = count + 1;                           //El contador aumenta en 1
            end
            else MDIO_out = MDIO_out ;                            //Si nada se cumple, todo permanece igual a como estaba.

        //Modo de Escritura    
        if (({T_data[N-2], T_data[N-3]} == 2'b01) && (count >= 1) && (count <= 32) && (reset == 1)) //Si el tercer y cuarto bit más significativos de T_data son 01, el modo es de escritura
            MDIO_oe <= 1;                                               //Si el contador indica un número entre 0 y 33, esta salida se pone en alto
        else MDIO_oe = 0;                                              //Si el contador indica un número igual o mayor a 33 esto quiere decir que la transmisión serial concluyó, por tanto MDIO_oe cae a 0

        //Modo de Lectura
        if (({T_data[N-2], T_data[N-3]} == 2'b10) && (count >= 1) && (count <= 16) && (reset == 1)) //Si el tercer y cuarto bit más significativos de T_data son 10, el modo es de lectura
            MDIO_oe <= 1;                                               //Si el contador indica un número entre 0 y 17, esta salida se pone en alto
        else MDIO_oe = 0;                                              //Si el contador indica un número igual o mayor a 17 implica que se está recibiendo el dato de MDIO_IN, por tanto cae a 0.



    //-------------------------------------------------------------------------------------------------------------------------------------------------------------
    //Modo lectura: Entrada serial a salida paralela

    //Modo de Lectura

        if ((MDIO_oe == 0) && (count >= 17) )                       //El MDIO_oe nos dice directamente si ya la transmisión de lectura por el MDIO_in comenzó
           wrtcount = wrtcount + 1;             //Se añade un contador de cara a poder indicar que la transferencia fue exitosa con el tamaño esperado
        else wrtcount = wrtcount; 

        if ((MDIO_oe == 0) && (wrtcount >= 17))                  //Cuando el contador de lectura esté entre 1 y 16, se estará en el proceso de transmisión
            data_RDY = 1;                        //Por lo tanto, RDY debe estar en bajo
        else data_RDY = 0;                       //Una vez que el contador supere los 16, quiere decir que los 16 bits fueron recibidos y la señal se pone en alto

        if ((MDIO_oe == 0) && (data_RDY == 0) && (1 <= wrtcount) && (wrtcount <= 16))        //Sabiendo que la transferencia de lectura inició, se realiza una rotación en la variable de almacenamiento de lectura
           almLEC = {MDIO_in, almLEC[(N-1)/2 : 1]}; //Esto se consigue ingresando hacia la izquierda con el valor de MDIO_in como la variable más significativa
        else almLEC = almLEC;                    //En caso de que MDIO_oe esté en uno, quiere decir que no se está en lectura, y si RDY está en bajo la transferencia no ha acabado 
        
        if (data_RDY == 1)        //Una vez que RDY se pone en alto, inmediatamente el valor de la variable de almacenamiento de lectura se carga en paralelo en RD_data
           RD_data <= almLEC ; 
        else RD_data = RD_data;              
    end






endmodule

testbench.v
`include "DUT.v"

module TransMDIO_tb;
reg clk, reset;
wire mdc;

wire MDIO_start;
reg [N:0] T_data1;
reg [N:0] T_data2;
reg [N:0] T_data3;
wire MDIO_out; 
wire MDIO_oe;

reg MDIO_in;
wire [(N-1)/2 : 0] RD_data;
wire data_RDY;


    parameter N = 31;

initial begin
	$dumpfile("MDIO_tb.vcd");
	$dumpvars(-1, PruebaEncendido);
	$dumpvars(-1, PruebaEscritura);
	$dumpvars(-1, PruebaLectura);
end


TransMDIO PruebaEncendido (

.clk            (clk),
.reset          (reset),
.mdc            (mdc),
.MDIO_start     (MDIO_start),
.T_data         (T_data1),
.MDIO_out       (MDIO_out),
.MDIO_oe        (MDIO_oe),
.MDIO_in        (MDIO_in),
.RD_data        (RD_data),
.data_RDY       (data_RDY)

);

TransMDIO PruebaEscritura (

.clk            (clk),
.reset          (reset),
.mdc            (mdc),
.MDIO_start     (MDIO_start),
.T_data         (T_data2),
.MDIO_out       (MDIO_out),
.MDIO_oe        (MDIO_oe),
.MDIO_in        (MDIO_in),
.RD_data        (RD_data),
.data_RDY       (data_RDY)

);


TransMDIO PruebaLectura (

.clk            (clk),
.reset          (reset),
.mdc            (mdc),
.MDIO_start     (MDIO_start),
.T_data         (T_data3),
.MDIO_out       (MDIO_out),
.MDIO_oe        (MDIO_oe),
.MDIO_in        (MDIO_in),
.RD_data        (RD_data),
.data_RDY       (data_RDY)

);



always begin
 #5 clk = ~clk; //Se define un periodo de 10 unidades de tiempo
end


//testbench encendido
//---------------------------------------------------------------------------------------------------
initial begin
clk = 0;
reset = 1;
T_data1 = 32'b00101111111001011001010001101101; //Esta señal no debe encender

#20 reset = 0; //Acá las salidas deben colocarse en 0, y almc = T_data
#60 reset = 1; //Acá vuelve a funcionar el circuito
#70 ; //Termina en 150 unidades de tiempo
end
//---------------------------------------------------------------------------------------------------


//Testbench escritura
//---------------------------------------------------------------------------------------------------
initial begin
clk = 0;
reset = 1;
T_data2 = 32'b01011111110010110010100011011011; //Esta señal debe encender y colocarse en modo escritura

#10 reset = 0; //Acá las salidas deben colocarse en 0, y almc = T_data
#60 reset = 1; //Acá vuelve a funcionar el circuito
#370 ; //Termina en 650 unidades de tiempo
end
//---------------------------------------------------------------------------------------------------


//Testbench lectura
//---------------------------------------------------------------------------------------------------
initial begin
clk = 0;
MDIO_in =0;
reset = 1;
T_data3 = 32'b01101111110010110010100011011011; //Esta señal debe encender y colocarse en modo lectura

#20 reset = 0; //Acá las salidas deben colocarse en 0, y almc = T_data
#60 reset = 1; //Acá vuelve a funcionar el circuito

#175 MDIO_in =0; //15  Acá se inicia la transacción de lectura
#10 MDIO_in =0;  //14
#10 MDIO_in =0;  //13
#10 MDIO_in =0;  //12
#10 MDIO_in =1;  //11
#10 MDIO_in =1;  //10
#10 MDIO_in =1;  //9
#10 MDIO_in =0;  //8
#10 MDIO_in =1;  //7
#10 MDIO_in =1;  //6
#10 MDIO_in =0;  //5
#10 MDIO_in =0;  //4
#10 MDIO_in =0;  //3
#10 MDIO_in =1;  //2
#10 MDIO_in =1;  //1
#10 MDIO_in =0;  //0

#70 $finish; //Termina el testbech
end







endmodule

MDIO_tb.vcd
$date
	Sat Jun 29 18:48:30 2024
$end
$version
	Icarus Verilog
$end
$timescale
	1s
$end
$scope module TransMDIO_tb $end
$scope module PruebaEncendido $end
$var wire 1 ! MDIO_in $end
$var wire 32 " T_data [31:0] $end
$var wire 1 # clk $end
$var wire 1 $ reset $end
$var reg 1 % MDIO_oe $end
$var reg 1 & MDIO_out $end
$var reg 1 ' MDIO_start $end
$var reg 16 ( RD_data [15:0] $end
$var reg 16 ) almLEC [15:0] $end
$var reg 32 * almc [31:0] $end
$var reg 6 + count [5:0] $end
$var reg 1 , data_RDY $end
$var reg 1 - freqcounter $end
$var reg 1 . mdc $end
$var reg 3 / nxt_state [2:0] $end
$var reg 3 0 state [2:0] $end
$var reg 6 1 wrtcount [5:0] $end
$upscope $end
$upscope $end
$scope module TransMDIO_tb $end
$scope module PruebaEscritura $end
$var wire 1 ! MDIO_in $end
$var wire 32 2 T_data [31:0] $end
$var wire 1 # clk $end
$var wire 1 $ reset $end
$var reg 1 3 MDIO_oe $end
$var reg 1 4 MDIO_out $end
$var reg 1 5 MDIO_start $end
$var reg 16 6 RD_data [15:0] $end
$var reg 16 7 almLEC [15:0] $end
$var reg 32 8 almc [31:0] $end
$var reg 6 9 count [5:0] $end
$var reg 1 : data_RDY $end
$var reg 1 ; freqcounter $end
$var reg 1 < mdc $end
$var reg 3 = nxt_state [2:0] $end
$var reg 3 > state [2:0] $end
$var reg 6 ? wrtcount [5:0] $end
$upscope $end
$upscope $end
$scope module TransMDIO_tb $end
$scope module PruebaLectura $end
$var wire 1 ! MDIO_in $end
$var wire 32 @ T_data [31:0] $end
$var wire 1 # clk $end
$var wire 1 $ reset $end
$var reg 1 A MDIO_oe $end
$var reg 1 B MDIO_out $end
$var reg 1 C MDIO_start $end
$var reg 16 D RD_data [15:0] $end
$var reg 16 E almLEC [15:0] $end
$var reg 32 F almc [31:0] $end
$var reg 6 G count [5:0] $end
$var reg 1 H data_RDY $end
$var reg 1 I freqcounter $end
$var reg 1 J mdc $end
$var reg 3 K nxt_state [2:0] $end
$var reg 3 L state [2:0] $end
$var reg 6 M wrtcount [5:0] $end
$upscope $end
$upscope $end
$enddefinitions $end
#0
$dumpvars
bx M
bx L
b1 K
xJ
0I
xH
bx G
bx F
bx E
bx D
xC
xB
xA
b1101111110010110010100011011011 @
bx ?
bx >
b1 =
x<
0;
x:
bx 9
bx 8
bx 7
bx 6
x5
x4
x3
b1011111110010110010100011011011 2
bx 1
bx 0
b1 /
x.
0-
x,
bx +
bx *
bx )
bx (
x'
x&
x%
1$
0#
b101111111001011001010001101101 "
0!
$end
#5
b10 /
b10 =
b10 K
1.
1-
b1 0
1<
1;
b1 >
1J
1I
b1 L
0,
0%
0:
03
0H
0A
1#
#10
0#
0$
#15
0I
0;
0-
b0 M
b0 E
b0 D
0J
b0 G
b1101111110010110010100011011011 F
0B
b0 ?
b0 7
b0 6
0<
b0 9
b1011111110010110010100011011011 8
04
b0 1
b0 )
b0 (
0.
b0 +
b101111111001011001010001101101 *
0&
1#
#20
0#
#25
1.
1-
1<
1;
1J
1I
1#
#30
0#
#35
0I
0;
0-
0J
0<
0.
1#
#40
0#
#45
1.
1-
1<
1;
1J
1I
1#
#50
0#
#55
0I
0;
0-
0J
0<
0.
1#
#60
0#
#65
1.
1-
1<
1;
1J
1I
1#
#70
0#
1$
#75
b100 K
b100 =
b10 L
0J
0I
b10 >
0<
0;
b10 0
0.
0-
1#
#80
0#
#85
15
1C
1.
1-
1<
1;
b100 >
1J
1I
b100 L
1#
#90
0#
#95
1A
0J
0I
13
0<
0;
0.
0-
b1 G
b11011111100101100101000110110110 F
b1 9
b10111111100101100101000110110110 8
1#
#100
0#
#105
1.
1-
1<
1;
1J
1I
13
b10 9
b1111111001011001010001101101100 8
14
1A
b10 G
b10111111001011001010001101101100 F
1B
1#
#110
0#
#115
0J
0I
0<
0;
0.
0-
1A
b11 G
b1111110010110010100011011011000 F
13
b11 9
b11111110010110010100011011011000 8
04
1#
#120
0#
#125
1.
1-
1<
1;
1J
1I
13
b100 9
b11111100101100101000110110110000 8
14
1A
b100 G
b11111100101100101000110110110000 F
0B
1#
#130
0#
#135
0J
0I
0<
0;
0.
0-
1A
b101 G
b11111001011001010001101101100000 F
1B
13
b101 9
b11111001011001010001101101100000 8
1#
#140
0#
#145
1.
1-
1<
1;
1J
1I
13
b110 9
b11110010110010100011011011000000 8
1A
b110 G
b11110010110010100011011011000000 F
1#
#150
0#
#155
0J
0I
0<
0;
0.
0-
1A
b111 G
b11100101100101000110110110000000 F
13
b111 9
b11100101100101000110110110000000 8
1#
#160
0#
#165
1.
1-
1<
1;
1J
1I
13
b1000 9
b11001011001010001101101100000000 8
1A
b1000 G
b11001011001010001101101100000000 F
1#
#170
0#
#175
0J
0I
0<
0;
0.
0-
1A
b1001 G
b10010110010100011011011000000000 F
13
b1001 9
b10010110010100011011011000000000 8
1#
#180
0#
#185
1.
1-
1<
1;
1J
1I
13
b1010 9
b101100101000110110110000000000 8
1A
b1010 G
b101100101000110110110000000000 F
1#
#190
0#
#195
0J
0I
0<
0;
0.
0-
1A
b1011 G
b1011001010001101101100000000000 F
0B
13
b1011 9
b1011001010001101101100000000000 8
04
1#
#200
0#
#205
1.
1-
1<
1;
1J
1I
13
b1100 9
b10110010100011011011000000000000 8
1A
b1100 G
b10110010100011011011000000000000 F
1#
#210
0#
#215
0J
0I
0<
0;
0.
0-
1A
b1101 G
b1100101000110110110000000000000 F
1B
13
b1101 9
b1100101000110110110000000000000 8
14
1#
#220
0#
#225
1.
1-
1<
1;
1J
1I
13
b1110 9
b11001010001101101100000000000000 8
04
1A
b1110 G
b11001010001101101100000000000000 F
0B
1#
#230
0#
#235
0J
0I
0<
0;
0.
0-
1A
b1111 G
b10010100011011011000000000000000 F
1B
13
b1111 9
b10010100011011011000000000000000 8
14
1#
#240
0#
#245
1.
1-
1<
1;
1J
1I
13
b10000 9
b101000110110110000000000000000 8
1A
b10000 G
b101000110110110000000000000000 F
1#
#250
0#
#255
0J
0I
0<
0;
0.
0-
b1 M
0A
b10001 G
b1010001101101100000000000000000 F
0B
b1 ?
13
b10001 9
b1010001101101100000000000000000 8
04
1#
#260
0#
#265
1.
1-
1<
1;
1J
1I
b10 ?
13
b10010 9
b10100011011011000000000000000000 8
b10 M
b10010 G
b10100011011011000000000000000000 F
1#
#270
0#
#275
0J
0I
0<
0;
0.
0-
b11 M
b10011 G
b1000110110110000000000000000000 F
1B
b11 ?
13
b10011 9
b1000110110110000000000000000000 8
14
1#
#280
0#
#285
1.
1-
1<
1;
1J
1I
b100 ?
13
b10100 9
b10001101101100000000000000000000 8
04
b100 M
b10100 G
b10001101101100000000000000000000 F
0B
1#
#290
0#
#295
0J
0I
0<
0;
0.
0-
b1000000000000000 E
b101 M
b10101 G
b11011011000000000000000000000 F
1B
b1000000000000000 7
b101 ?
13
b10101 9
b11011011000000000000000000000 8
14
1#
1!
#300
0#
#305
1.
1-
1<
1;
1J
1I
b1100000000000000 7
b110 ?
13
b10110 9
b110110110000000000000000000000 8
04
b1100000000000000 E
b110 M
b10110 G
b110110110000000000000000000000 F
0B
1#
#310
0#
#315
0J
0I
0<
0;
0.
0-
b1110000000000000 E
b111 M
b10111 G
b1101101100000000000000000000000 F
b1110000000000000 7
b111 ?
13
b10111 9
b1101101100000000000000000000000 8
1#
#320
0#
#325
1.
1-
1<
1;
1J
1I
b111000000000000 7
b1000 ?
13
b11000 9
b11011011000000000000000000000000 8
b111000000000000 E
b1000 M
b11000 G
b11011011000000000000000000000000 F
1#
0!
#330
0#
#335
0J
0I
0<
0;
0.
0-
b1011100000000000 E
b1001 M
b11001 G
b10110110000000000000000000000000 F
1B
b1011100000000000 7
b1001 ?
13
b11001 9
b10110110000000000000000000000000 8
14
1#
1!
#340
0#
#345
1.
1-
1<
1;
1J
1I
b1101110000000000 7
b1010 ?
13
b11010 9
b1101100000000000000000000000000 8
b1101110000000000 E
b1010 M
b11010 G
b1101100000000000000000000000000 F
1#
#350
0#
#355
0J
0I
0<
0;
0.
0-
b110111000000000 E
b1011 M
b11011 G
b11011000000000000000000000000000 F
0B
b110111000000000 7
b1011 ?
13
b11011 9
b11011000000000000000000000000000 8
04
1#
0!
#360
0#
#365
1.
1-
1<
1;
1J
1I
b11011100000000 7
b1100 ?
13
b11100 9
b10110000000000000000000000000000 8
14
b11011100000000 E
b1100 M
b11100 G
b10110000000000000000000000000000 F
1B
1#
#370
0#
#375
0J
0I
0<
0;
0.
0-
b1101110000000 E
b1101 M
b11101 G
b1100000000000000000000000000000 F
b1101110000000 7
b1101 ?
13
b11101 9
b1100000000000000000000000000000 8
1#
#380
0#
#385
1.
1-
1<
1;
1J
1I
b1000110111000000 7
b1110 ?
13
b11110 9
b11000000000000000000000000000000 8
04
b1000110111000000 E
b1110 M
b11110 G
b11000000000000000000000000000000 F
0B
1#
1!
#390
0#
#395
0J
0I
0<
0;
0.
0-
b1100011011100000 E
b1111 M
b11111 G
b10000000000000000000000000000000 F
1B
b1100011011100000 7
b1111 ?
13
b11111 9
b10000000000000000000000000000000 8
14
1#
#400
0#
#405
1.
1-
1<
1;
1J
1I
b110001101110000 7
b10000 ?
13
b100000 9
b0 8
b110001101110000 E
b10000 M
b100000 G
b0 F
1#
0!
#410
0#
#415
b110001101110000 D
0J
0I
b110001101110000 6
0<
0;
0.
0-
1H
b10001 M
b100001 G
0B
1:
b10001 ?
03
b100001 9
04
1#
#420
0#
#425
1.
1-
1<
1;
1J
1I
b10010 ?
b100010 9
b10010 M
b100010 G
1#
#430
0#
#435
0J
0I
0<
0;
0.
0-
b10011 M
b100011 G
b10011 ?
b100011 9
1#
#440
0#
#445
1.
1-
1<
1;
1J
1I
b10100 ?
b100100 9
b10100 M
b100100 G
1#
#450
0#
#455
0J
0I
0<
0;
0.
0-
b10101 M
b100101 G
b10101 ?
b100101 9
1#
#460
0#
#465
1.
1-
1<
1;
1J
1I
b10110 ?
b100110 9
b10110 M
b100110 G
1#
#470
0#
#475
0J
0I
0<
0;
0.
0-
b10111 M
b100111 G
b10111 ?
b100111 9
1#
