tester_dut1.v
module tester_dut1(
    output reg clk,
    output reg reset,
    output reg mdio_start,
    output reg [31:0] t_data,
    output reg mdio_in,
    input rd_data,
    input data_rdy,
    input mdc,
    input mdio_oe,
    input mdio_out
);

//acá se definen las pruebas que se van a realizar
always begin//inicializamos el clk
    #2 clk = ~clk;
end

//prueba de encendido
//preguntar: ¿pongo todas las pruebas en un solo intial begin? tengo un ejemplo en el que vene cada una en une indidtal begin por aparte.
initial  begin
    clk = 0;
    reset = 0;

    #10 reset = 1;

    //se prueba la máquina de estados
    #10 t_data = 32'b01101111111001011001010001101111;//con este número deberia pasar al 2do estado

    #100;
    $finish;
end
endmodule

dut1.v
module dut1 (
  input clk,
  input reset,//cuando reset = 1 el generador funciona con normalidad.
              //si reset = 0, el generador vuelve a estado incial y todas las salidas a 0.
  input mdio_start,
  input [31:0] t_data,
  input mdio_in,
  output reg [15:0] rd_data,
  output reg data_rdy,
  output reg mdc,
  output reg mdio_oe,//indentifica el tipo de transacción (lectura o escritura)
  output reg mdio_out//salida serial se habilita cuando mdio_start = 1.
                     //por esta salida se envían los bits que se reciben por t_data.
);

//variables internas para la máquinas de estados
reg [2:0] state;
reg [2:0] next_state;

//variables internas para ka transacción
reg [15:0] almacenamiento; //guarda los bits obtenidos en MDIO_in *preguntar ¿no sería más bien los bits de t_data
reg [5:0] count; //contador
reg cout_freq = 0;//determina si la frecuencia de salida se coloca en alto o bajo
reg [7:0] almacenamiento_lectura;//guarda los valores que serán cargados a rd_data
reg [5:0] wrtcount;//cuenta los bits leídos cuando se comienza la transferencia por mdio_in

parameter freqdiv = 10'd2;//dividiremos la frecuencia por 2.

//se genera el mdc:
always @(posedge clk) begin
  if (!reset)begin
    count <= 0;
    mdc <= 0;
  end

  else begin
    count <= count + 0.5;
    if(count == 1) begin
      count <= 0;
      mdc <= ~mdc;
      //$display("mdc");
    end
  end 
    
  /*else begin
    mdc = 0;
    $display("mdc_else %d", count);
  end*/
end

always @(posedge clk) begin
//efecto del reset:
  if (reset == 0)begin //cuando reset esté en bajo se regresa al estado inicial y todas las salidas se ponene en 0
    mdio_out = 0;
    almacenamiento = t_data;
    count = 0;
    mdc = 0;
    mdio_oe = 0;
    rd_data = 0;
    data_rdy = 0;
    almacenamiento_lectura = 0;
    wrtcount = 0;
  end 
  else begin //funcionaminento normal
    mdio_out = mdio_out;
    almacenamiento = almacenamiento;
    mdio_oe = mdio_oe;
    rd_data = rd_data;
    data_rdy = data_rdy;
    almacenamiento_lectura = almacenamiento_lectura;
    wrtcount = wrtcount;
  end
end

//entrada de salida paralela a salida parcial
always @(*)begin
  if (~reset)
    state = 3'b001; //cuando reset = 0, se vuelve al estado idle
  else
    next_state = state;
end

always @(*)begin
  $display("%d", t_data[31]);
  case (state)
    3'b001: begin
      if(t_data[31] == 0)//el último bit de t_data es 0
        state = 3'b010;
      else
        state = 3'b001;
    end

    3'b010: begin
      if(t_data[30] == 1)
        state = 3'b100;
      else 
        state = 3'b010;
    end

    3'b100: begin
      //se inicia la transacción de datos
      $display("mdio_out");
    end

    default: next_state = 3'b001; //si se recibe un valor no definido se vuelve a idle
  endcase
end
endmodule

testbench_dut1.v
`include "dut1.v"
`include "tester_dut1.v"

module testbench_dut1;
//wires del testbench
wire clk, reset;
wire mdio_start; 
wire mdio_in;
wire [31:0] t_data; //preguntar: ¿estp está bien como reg o mejor que sea wire?
wire [15:0] rd_data;
wire data_rdy, mdc, mdio_oe, mdio_out;

//se conecta el DUT
dut1 DUT (
    .clk(clk),
    .reset(reset),
    .mdio_start(mdio_start),
    .t_data(t_data[31:0]),
    .mdio_in(mdio_in),
    .rd_data(rd_data[15:0]),
    .data_rdy(data_rdy),
    .mdc(mdc),
    .mdio_oe(mdio_oe),
    .mdio_out(mdio_out)
);

tester_dut1 test (
    .clk(clk),
    .reset(reset),
    .mdio_start(mdio_start),
    .t_data(t_data[31:0]),
    .mdio_in(mdio_in),
    .rd_data(rd_data[15:0]),
    .data_rdy(data_rdy),
    .mdc(mdc),
    .mdio_oe(mdio_oe),
    .mdio_out(mdio_out)
);

//para monitorear las pruebas:
initial begin
    $dumpfile("tb.vcd");
    $dumpvars;
end
endmodule

tb.vcd
$date
	Tue Jun 18 20:25:19 2024
$end
$version
	Icarus Verilog
$end
$timescale
	1s
$end
$scope module testbench_dut1 $end
$var wire 32 ! t_data [31:0] $end
$var wire 1 " reset $end
$var wire 16 # rd_data [15:0] $end
$var wire 1 $ mdio_start $end
$var wire 1 % mdio_out $end
$var wire 1 & mdio_oe $end
$var wire 1 ' mdio_in $end
$var wire 1 ( mdc $end
$var wire 1 ) data_rdy $end
$var wire 1 * clk $end
$scope module DUT $end
$var wire 32 + t_data [31:0] $end
$var wire 1 " reset $end
$var wire 1 $ mdio_start $end
$var wire 1 ' mdio_in $end
$var wire 1 * clk $end
$var reg 16 , almacenamiento [15:0] $end
$var reg 8 - almacenamiento_lectura [7:0] $end
$var reg 6 . count [5:0] $end
$var reg 1 / cout_freq $end
$var reg 1 ) data_rdy $end
$var reg 1 ( mdc $end
$var reg 1 & mdio_oe $end
$var reg 1 % mdio_out $end
$var reg 3 0 next_state [2:0] $end
$var reg 16 1 rd_data [15:0] $end
$var reg 3 2 state [2:0] $end
$var reg 6 3 wrtcount [5:0] $end
$upscope $end
$scope module test $end
$var wire 1 ) data_rdy $end
$var wire 1 ( mdc $end
$var wire 1 & mdio_oe $end
$var wire 1 % mdio_out $end
$var wire 1 4 rd_data $end
$var reg 1 * clk $end
$var reg 1 ' mdio_in $end
$var reg 1 $ mdio_start $end
$var reg 1 " reset $end
$var reg 32 5 t_data [31:0] $end
$upscope $end
$upscope $end
$enddefinitions $end
#0
$dumpvars
bx 5
x4
bx 3
b1 2
bx 1
bx 0
0/
bx .
bx -
bx ,
bx +
0*
x)
x(
x'
x&
x%
x$
bx #
0"
bx !
$end
#2
04
b0 3
b0 -
0)
b0 #
b0 1
0&
0(
b0 .
0%
1*
#4
0*
#6
1*
#8
0*
#10
b1 .
b1 0
1*
1"
#12
0*
#14
1(
b0 .
1*
#16
0*
#18
b1 .
1*
#20
b10 0
b10 2
0*
b1101111111001011001010001101111 !
b1101111111001011001010001101111 +
b1101111111001011001010001101111 5
#22
0(
b0 .
1*
#24
0*
#26
b1 .
1*
#28
0*
#30
1(
b0 .
1*
#32
0*
#34
b1 .
1*
#36
0*
#38
0(
b0 .
1*
#40
0*
#42
b1 .
1*
#44
0*
#46
1(
b0 .
1*
#48
0*
#50
b1 .
1*
#52
0*
#54
0(
b0 .
1*
#56
0*
#58
b1 .
1*
#60
0*
#62
1(
b0 .
1*
#64
0*
#66
b1 .
1*
#68
0*
#70
0(
b0 .
1*
#72
0*
#74
b1 .
1*
#76
0*
#78
1(
b0 .
1*
#80
0*
#82
b1 .
1*
#84
0*
#86
0(
b0 .
1*
#88
0*
#90
b1 .
1*
#92
0*
#94
1(
b0 .
1*
#96
0*
#98
b1 .
1*
#100
0*
#102
0(
b0 .
1*
#104
0*
#106
b1 .
1*
#108
0*
#110
1(
b0 .
1*
#112
0*
#114
b1 .
1*
#116
0*
#118
0(
b0 .
1*
