tester_dut1.v
module tester_dut1(
    output reg clk,
    output reg reset,
    output reg mdio_start,
    output reg [31:0] t_data,
    output reg mdio_in,
    input rd_data,
    input data_rdy,
    input mdc,
    input mdio_oe,
    input mdio_out
);

//acá se definen las pruebas que se van a realizar
always begin//inicializamos el clk
    #2 clk = ~clk;
end

//prueba de encendido
//preguntar: ¿pongo todas las pruebas en un solo intial begin? tengo un ejemplo en el que vene cada una en une indidtal begin por aparte.
initial  begin
    clk = 0;
    reset = 0;

    #10 reset = 1;

    //se prueba la máquina de estados
    #10 t_data = 32'b01101111111001011001010001101111;//con este número deberia pasar al 2do estado

    #10 t_data = 32'b01001111111001011001010001101111;//con este número pasa al tercer estado
    
    #10 t_data = 32'b01100111111001011001010001101111;
    mdio_start = 1;
    #4 mdio_start = 0;

    #70;

    //se prueba el modo escritura
    //reset = 1;
    #10 t_data = 32'b01011111110010110010100011011011;

    #70;

    //se prueba el modo lectura
    #10 t_data = 32'b01101111110010110010100011011011;

    #15 mdio_in =0; //15  Acá se inicia la transacción de lectura
    #10 mdio_in =0;  //14
    #10 mdio_in =0;  //13
    #10 mdio_in =0;  //12
    #10 mdio_in =1;  //11
    #10 mdio_in =1;  //10
    #10 mdio_in =1;  //9
    #10 mdio_in =0;  //8
    #10 mdio_in =1;  //7
    #10 mdio_in =1;  //6
    #10 mdio_in =0;  //5
    #10 mdio_in =0;  //4
    #10 mdio_in =0;  //3
    #10 mdio_in =1;  //2
    #10 mdio_in =1;  //1
    #10 mdio_in =0;  //0
    
    #100;
    $finish;
end
endmodule

dut1.v
module dut1 (
  input clk,
  input reset,//cuando reset = 1 el generador funciona con normalidad.
              //si reset = 0, el generador vuelve a estado incial y todas las salidas a 0.
  input mdio_start,
  input [31:0] t_data,
  input mdio_in,
  output reg [15:0] rd_data,
  output reg data_rdy,
  output reg mdc,
  output reg mdio_oe,//indentifica el tipo de transacción (lectura o escritura)
  output reg mdio_out//salida serial se habilita cuando mdio_start = 1.
                     //por esta salida se envían los bits que se reciben por t_data.
);

//variables internas para la máquinas de estados
reg [2:0] state;
reg [2:0] next_state;
//reg [31:0] almacen; //agregado por auro para lo de lectura/escritura

//variables internas para la transacción
reg [15:0] almacenamiento; //guarda los bits obtenidos en MDIO_in *preguntar ¿no sería más bien los bits de t_data
reg [5:0] count; //contador
//reg cout_freq = 0;//determina si la frecuencia de salida se coloca en alto o bajo
reg [15:0] almacenamiento_lectura;//guarda los valores que serán cargados a rd_data
reg [5:0] wrtcount;//cuenta los bits leídos cuando se comienza la transferencia por mdio_in
reg start; //me indica que el dato es válido para iniciar la lectura/transmision de datos

//parameter freqdiv = 10'd2;//dividiremos la frecuencia por 2.
//linea de arriba no se usa 
//se genera el mdc:
always @(posedge clk) begin
  if (!reset)begin
    count <= 0;
    mdc <= 0;
  end

  else begin
    count <= count + 0.5;
    if(count == 1) begin
      count <= 0;
      mdc <= ~mdc;
      //$display("mdc");
    end
  end 
    
  /*else begin
    mdc = 0;
    $display("mdc_else %d", count);
  end*/
end

always @(posedge clk) begin
//efecto del reset:
  if (reset == 0)begin //cuando reset esté en bajo se regresa al estado inicial y todas las salidas se ponene en 0
    mdio_out = 0;
    almacenamiento = t_data;
    count = 0;
    mdc = 0;
    mdio_oe = 0;
    rd_data = 0;
    data_rdy = 0;
    almacenamiento_lectura = 0;
    wrtcount = 0;
  end 
  else begin //funcionaminento normal
    mdio_out = mdio_out;
    almacenamiento = almacenamiento;
    mdio_oe = mdio_oe;
    rd_data = rd_data;
    data_rdy = data_rdy;
    almacenamiento_lectura = almacenamiento_lectura;
    wrtcount = wrtcount;
  end
end

//entrada de salida paralela a salida parcial
//acá se selecciona si la información es adecuada para ser transmitida por el protocolo (ya que los bits 31 y 30 siempre deben ser 0 y 1)
always @(posedge clk)begin
  if (~reset)
    state <= 3'b001; //cuando reset = 0, se vuelve al estado idle
  else
    next_state <= state;
end

always @(*)begin
  $display("%d", t_data[31]);
  $display("%d", t_data[30]);
  case (state)
    3'b001: begin //idle
      if(t_data[31] == 0)
        state = 3'b010;
      else 
        state = 3'b001;
    end

    3'b010: begin//se revisa el bit 30 de la información a transmitir
    //se pasan los 32 bits de t_data
    // se tienen que pasar cada que mdc está en alto
    //en modo escritura está en alto siempre que esté activo el modo escritura
      /*if(mdio_start == 1) begin
        mdc <= 1;
        if(count < 31) begin
          mdio_out <= t_data[count]; //mdio_out agarra el valor de t_data
          mdio_oe <= 1;
          count <= count + 1;
        end
        //$display("%b", t_data);
      end*/

      if(t_data[30] == 1)
        state = 3'b100;
      else 
        state = 3'b010;
    end
    /*3:begin //acá el contador cuenta
      mdc <= 0;
      if(count > 0)begin
        state <= 2;
      end
    end*/

    3'b100: begin//este sería el estado de lectura
      //solo se pasan los primeros 16
      //mdio_oe estaría en alto solo cuando se transmite t_data (16 ciclos)
      //cuando se leen datos mdio_oe tiene que estar en bajo cuando se reciben datos
        /*if(count < 15) begin
          mdio_oe <= 1;
          count <= count + 1;
          state <= 5;
        end*/
      if(mdio_start == 1) begin
        //mdio_out = t_data; //mdio_out agarra el valor de t_data
        start = 1;
        $display("%b", t_data);
      end
      //hay que recibir los datos y se guaran en un registro interno.
      //luego se sacan por rd_data
    end

    default: state = 3'b001; //si se recibe un valor no definido se vuelve a idle
  endcase
end

//una vez que el dato se toma como aceptable, se programan los modos escritura y lectura
always @(posedge clk)begin
  if((t_data[31:0] == almacenamiento[31:0]) && (reset == 1) && (start == 1)) begin
    mdio_out = almacenamiento[31];
    almacenamiento = {almacenamiento[30:0], 1'b0};

    count = count + 1;
  end
  else if ((t_data[31:0] != almacenamiento[31:0]) && (reset == 1) && (start == 1)) begin
    mdio_out = almacenamiento[31];
    almacenamiento = {almacenamiento[30:0], 1'b0};

    count = count + 1;
  end
  else
    mdio_out = mdio_out;

  //modo de escritura
  if ((t_data[29:28] == 2'b01) && (count <= 31) && (reset == 1))
    mdio_oe = 1; //mdio_oe está en alto siempre que se estén transmitiendo datos.

  /*else
    mdio_oe <= 0;*/

  //modo de lectura
  if ((t_data[29:28] == 2'b10) && (count <= 15) && (reset == 1))
    mdio_oe <= 1; //mdio_oe solo está en alto durante 16 bits de la transacción en modo lectura

  /*else
    mdio_oe <= 0;*/

  //modo de lectura: entrada serial a salida paralela
  //modo de lectura
  if ((mdio_oe == 0) && (count >= 15)) //mdio_oe nos dice si ya inició o terminó la transmisión de lectura por mdio_in
    wrtcount = wrtcount + 1;
  else 
    wrtcount =wrtcount;

  if ((mdio_oe == 0) && (wrtcount >= 15))
    data_rdy <= 1;
  /*else
    data_rdy <= 0;*/

  if ((mdio_oe == 0) && (data_rdy == 0) && (1 <= wrtcount) && (wrtcount <= 16))
    almacenamiento_lectura = {mdio_in, almacenamiento_lectura[15:1]};
  else 
    almacenamiento_lectura = almacenamiento_lectura;

  if(data_rdy == 1)
    rd_data <= almacenamiento_lectura;
  else
    rd_data <= rd_data;
end
endmodule

testbench_dut1.v
`include "dut1.v"
`include "tester_dut1.v"

module testbench_dut1;
//wires del testbench
wire clk, reset;
wire mdio_start; 
wire mdio_in;
wire [31:0] t_data; //preguntar: ¿estp está bien como reg o mejor que sea wire?
wire [15:0] rd_data;
wire data_rdy, mdc, mdio_oe, mdio_out;

//se conecta el DUT
dut1 DUT (
    .clk(clk),
    .reset(reset),
    .mdio_start(mdio_start),
    .t_data(t_data[31:0]),
    .mdio_in(mdio_in),
    .rd_data(rd_data[15:0]),
    .data_rdy(data_rdy),
    .mdc(mdc),
    .mdio_oe(mdio_oe),
    .mdio_out(mdio_out)
);

tester_dut1 test (
    .clk(clk),
    .reset(reset),
    .mdio_start(mdio_start),
    .t_data(t_data[31:0]),
    .mdio_in(mdio_in),
    .rd_data(rd_data[15:0]),
    .data_rdy(data_rdy),
    .mdc(mdc),
    .mdio_oe(mdio_oe),
    .mdio_out(mdio_out)
);

//para monitorear las pruebas:
initial begin
    $dumpfile("tb.vcd");
    $dumpvars;
end
endmodule

tb.vcd
$date
	Sun Jun 30 12:44:42 2024
$end
$version
	Icarus Verilog
$end
$timescale
	1s
$end
$scope module testbench_dut1 $end
$var wire 32 ! t_data [31:0] $end
$var wire 1 " reset $end
$var wire 16 # rd_data [15:0] $end
$var wire 1 $ mdio_start $end
$var wire 1 % mdio_out $end
$var wire 1 & mdio_oe $end
$var wire 1 ' mdio_in $end
$var wire 1 ( mdc $end
$var wire 1 ) data_rdy $end
$var wire 1 * clk $end
$scope module DUT $end
$var wire 32 + t_data [31:0] $end
$var wire 1 " reset $end
$var wire 1 $ mdio_start $end
$var wire 1 ' mdio_in $end
$var wire 1 * clk $end
$var reg 16 , almacenamiento [15:0] $end
$var reg 16 - almacenamiento_lectura [15:0] $end
$var reg 6 . count [5:0] $end
$var reg 1 ) data_rdy $end
$var reg 1 ( mdc $end
$var reg 1 & mdio_oe $end
$var reg 1 % mdio_out $end
$var reg 3 / next_state [2:0] $end
$var reg 16 0 rd_data [15:0] $end
$var reg 1 1 start $end
$var reg 3 2 state [2:0] $end
$var reg 6 3 wrtcount [5:0] $end
$upscope $end
$scope module test $end
$var wire 1 ) data_rdy $end
$var wire 1 ( mdc $end
$var wire 1 & mdio_oe $end
$var wire 1 % mdio_out $end
$var wire 1 4 rd_data $end
$var reg 1 * clk $end
$var reg 1 ' mdio_in $end
$var reg 1 $ mdio_start $end
$var reg 1 " reset $end
$var reg 32 5 t_data [31:0] $end
$upscope $end
$upscope $end
$enddefinitions $end
#0
$dumpvars
bx 5
x4
bx 3
bx 2
x1
bx 0
bx /
bx .
bx -
bx ,
bx +
0*
x)
x(
x'
x&
x%
x$
bx #
0"
bx !
$end
#2
b1 2
x4
b0 3
b0 -
0)
bx #
bx 0
0&
0(
b0 .
0%
1*
#4
0*
#6
04
b0 #
b0 0
1*
#8
0*
#10
b1 .
b1 /
1*
1"
#12
0*
#14
1(
b0 .
1*
#16
0*
#18
b1 .
1*
#20
b10 2
0*
b1101111111001011001010001101111 !
b1101111111001011001010001101111 +
b1101111111001011001010001101111 5
#22
1&
b10 /
0(
b0 .
1*
#24
0*
#26
b1 .
1*
#28
0*
#30
b100 /
1(
b0 .
b100 2
1*
b1001111111001011001010001101111 !
b1001111111001011001010001101111 +
b1001111111001011001010001101111 5
#32
0*
#34
b1 .
1*
#36
0*
#38
0(
b0 .
1*
#40
11
0*
1$
b1100111111001011001010001101111 !
b1100111111001011001010001101111 +
b1100111111001011001010001101111 5
#42
b1 .
1*
#44
0*
0$
#46
1(
b0 .
1*
#48
0*
#50
b1 .
1*
#52
0*
#54
0(
b0 .
1*
#56
0*
#58
b1 .
1*
#60
0*
#62
1(
b0 .
1*
#64
0*
#66
b1 .
1*
#68
0*
#70
0(
b0 .
1*
#72
0*
#74
b1 .
1*
#76
0*
#78
1(
b0 .
1*
#80
0*
#82
b1 .
1*
#84
0*
#86
0(
b0 .
1*
#88
0*
#90
b1 .
1*
#92
0*
#94
1(
b0 .
1*
#96
0*
#98
b1 .
1*
#100
0*
#102
0(
b0 .
1*
#104
0*
#106
b1 .
1*
#108
0*
#110
1(
b0 .
1*
#112
0*
#114
b1 .
1*
#116
0*
#118
0(
b0 .
1*
#120
0*
#122
b1 .
1*
#124
0*
b1011111110010110010100011011011 !
b1011111110010110010100011011011 +
b1011111110010110010100011011011 5
#126
1(
b0 .
1*
#128
0*
#130
b1 .
1*
#132
0*
#134
0(
b0 .
1*
#136
0*
#138
b1 .
1*
#140
0*
#142
1(
b0 .
1*
#144
0*
#146
b1 .
1*
#148
0*
#150
0(
b0 .
1*
#152
0*
#154
b1 .
1*
#156
0*
#158
1(
b0 .
1*
#160
0*
#162
b1 .
1*
#164
0*
#166
0(
b0 .
1*
#168
0*
#170
b1 .
1*
#172
0*
#174
1(
b0 .
1*
#176
0*
#178
b1 .
1*
#180
0*
#182
0(
b0 .
1*
#184
0*
#186
b1 .
1*
#188
0*
#190
1(
b0 .
1*
#192
0*
#194
b1 .
1*
#196
0*
#198
0(
b0 .
1*
#200
0*
#202
b1 .
1*
#204
0*
b1101111110010110010100011011011 !
b1101111110010110010100011011011 +
b1101111110010110010100011011011 5
#206
1(
b0 .
1*
#208
0*
#210
b1 .
1*
#212
0*
#214
0(
b0 .
1*
#216
0*
#218
b1 .
1*
#219
0'
#220
0*
#222
1(
b0 .
1*
#224
0*
#226
b1 .
1*
#228
0*
#230
0(
b0 .
1*
#232
0*
#234
b1 .
1*
#236
0*
#238
1(
b0 .
1*
#240
0*
#242
b1 .
1*
#244
0*
#246
0(
b0 .
1*
#248
0*
#250
b1 .
1*
#252
0*
#254
1(
b0 .
1*
#256
0*
#258
b1 .
1*
#259
1'
#260
0*
#262
0(
b0 .
1*
#264
0*
#266
b1 .
1*
#268
0*
#270
1(
b0 .
1*
#272
0*
#274
b1 .
1*
#276
0*
#278
0(
b0 .
1*
#280
0*
#282
b1 .
1*
#284
0*
#286
1(
b0 .
1*
#288
0*
#289
0'
#290
b1 .
1*
#292
0*
#294
0(
b0 .
1*
#296
0*
#298
b1 .
1*
#299
1'
#300
0*
#302
1(
b0 .
1*
#304
0*
#306
b1 .
1*
#308
0*
#310
0(
b0 .
1*
#312
0*
#314
b1 .
1*
#316
0*
#318
1(
b0 .
1*
#319
0'
#320
0*
#322
b1 .
1*
#324
0*
#326
0(
b0 .
1*
#328
0*
#330
b1 .
1*
#332
0*
#334
1(
b0 .
1*
#336
0*
#338
b1 .
1*
#340
0*
#342
0(
b0 .
1*
#344
0*
#346
b1 .
1*
#348
0*
#349
1'
#350
1(
b0 .
1*
#352
0*
#354
b1 .
1*
#356
0*
#358
0(
b0 .
1*
#360
0*
#362
b1 .
1*
#364
0*
#366
1(
b0 .
1*
#368
0*
#369
0'
#370
b1 .
1*
#372
0*
#374
0(
b0 .
1*
#376
0*
#378
b1 .
1*
#380
0*
#382
1(
b0 .
1*
#384
0*
#386
b1 .
1*
#388
0*
#390
0(
b0 .
1*
#392
0*
#394
b1 .
1*
#396
0*
#398
1(
b0 .
1*
#400
0*
#402
b1 .
1*
#404
0*
#406
0(
b0 .
1*
#408
0*
#410
b1 .
1*
#412
0*
#414
1(
b0 .
1*
#416
0*
#418
b1 .
1*
#420
0*
#422
0(
b0 .
1*
#424
0*
#426
b1 .
1*
#428
0*
#430
1(
b0 .
1*
#432
0*
#434
b1 .
1*
#436
0*
#438
0(
b0 .
1*
#440
0*
#442
b1 .
1*
#444
0*
#446
1(
b0 .
1*
#448
0*
#450
b1 .
1*
#452
0*
#454
0(
b0 .
1*
#456
0*
#458
b1 .
1*
#460
0*
#462
1(
b0 .
1*
#464
0*
#466
b1 .
1*
